mask_env/__init__.py
mask_env/cli.py
mask_env/core.py
mask_env/formats.py
mask_env/processor.py
mask_env-1.0.0.dist-info/METADATA
mask_env-1.0.0.dist-info/WHEEL
mask_env-1.0.0.dist-info/entry_points.txt
mask_env-1.0.0.dist-info/top_level.txt
mask_env-1.0.0.dist-info/RECORD
