Metadata-Version: 2.4
Name: mask-env
Version: 1.0.0
Summary: Create safe .example files from secret config files by masking sensitive values
Author: mask-env contributors
Author-email: Vishnu Prasad <vishnuprasadapp@gmail.com>
License: MIT
Project-URL: Homepage, https://github.com/VishApp/mask-env
Project-URL: Repository, https://github.com/VishApp/mask-env.git
Project-URL: Issues, https://github.com/VishApp/mask-env/issues
Keywords: env,environment,secrets,security,.env
Classifier: Development Status :: 5 - Production/Stable
Classifier: Intended Audience :: Developers
Classifier: License :: OSI Approved :: MIT License
Classifier: Programming Language :: Python :: 3
Classifier: Programming Language :: Python :: 3.7
Classifier: Programming Language :: Python :: 3.8
Classifier: Programming Language :: Python :: 3.9
Classifier: Programming Language :: Python :: 3.10
Classifier: Programming Language :: Python :: 3.11
Classifier: Programming Language :: Python :: 3.12
Classifier: Topic :: Security
Classifier: Topic :: Software Development :: Libraries :: Python Modules
Requires-Python: >=3.7
Provides-Extra: yaml
Requires-Dist: pyyaml>=6.0; extra == "yaml"
Provides-Extra: toml
Requires-Dist: tomli>=2.0; python_version < "3.11" and extra == "toml"
Requires-Dist: toml>=0.10; python_version >= "3.7" and extra == "toml"
